artgym_env/__init__.py
artgym_env/envs/__init__.py
artgym_env/envs/grid_world.py
artgym_env/envs/mujoco/leoquad_v4.py
artgym_env/envs/mujoco/assets/LeoQuad.xml
artgym_env/envs/mujoco/assets/ant.xml
artgym_env/envs/mujoco/assets/meshes/BL_CALF.STL
artgym_env/envs/mujoco/assets/meshes/BL_HP.STL
artgym_env/envs/mujoco/assets/meshes/BL_THIGH.STL
artgym_env/envs/mujoco/assets/meshes/BODY.STL
artgym_env/envs/mujoco/assets/meshes/BR_CALF.STL
artgym_env/envs/mujoco/assets/meshes/BR_HP.STL
artgym_env/envs/mujoco/assets/meshes/BR_THIGH.STL
artgym_env/envs/mujoco/assets/meshes/FL_CALF.STL
artgym_env/envs/mujoco/assets/meshes/FL_HP.STL
artgym_env/envs/mujoco/assets/meshes/FL_THIGH.STL
artgym_env/envs/mujoco/assets/meshes/FR_CALF.STL
artgym_env/envs/mujoco/assets/meshes/FR_HP.STL
artgym_env/envs/mujoco/assets/meshes/FR_THIGH.STL
artgym_env/wrappers/__init__.py
artgym_env/wrappers/clip_reward.py
artgym_env/wrappers/discrete_actions.py
artgym_env/wrappers/reacher_weighted_reward.py
artgym_env/wrappers/relative_position.py
artgym_env-0.0.2.dist-info/METADATA
artgym_env-0.0.2.dist-info/WHEEL
artgym_env-0.0.2.dist-info/licenses/LICENSE
artgym_env-0.0.2.dist-info/RECORD
