Metadata-Version: 2.4
Name: artgym_env
Version: 0.0.2
Summary: Gymnasium environments and wrappers published by ART team. It is a part of ART-Framework(TM) and ART-Gym(TM).
Author-email: Sean Yi <sangyobe@gmail.com>, Sean Yi <sean.yi@hyundai.com>
License-File: LICENSE
Keywords: art framework,gymnasium,leoquad,mujoco,reinforcement learning
Classifier: License :: OSI Approved :: MIT License
Classifier: Operating System :: OS Independent
Classifier: Programming Language :: Python :: 3
Requires-Python: >=3.7
Requires-Dist: gymnasium
Requires-Dist: pre-commit
Requires-Dist: pygame>=2.1.3
